setup.py
transitland/__init__.py
transitland/__main__.py
transitland/bootstrap.py
transitland/datastore.py
transitland/entities.py
transitland/entity.py
transitland/errors.py
transitland/feed.py
transitland/fetch.py
transitland/geom.py
transitland/operator.py
transitland/registry.py
transitland/route.py
transitland/stop.py
transitland/test_entities.py
transitland/test_entity.py
transitland/test_feed.py
transitland/test_geom.py
transitland/test_operator.py
transitland/test_registry.py
transitland/test_route.py
transitland/test_stop.py
transitland/test_util.py
transitland/util.py
transitland.egg-info/PKG-INFO
transitland.egg-info/SOURCES.txt
transitland.egg-info/dependency_links.txt
transitland.egg-info/not-zip-safe
transitland.egg-info/requires.txt
transitland.egg-info/top_level.txt