Metadata-Version: 1.0
Name: transitland
Version: 0.5.6
Summary: Transitland Client
Home-page: https://github.com/transitland/transitland-python-client
Author: Ian Rees
Author-email: ian@mapzen.com
License: License :: OSI Approved :: MIT License
Platform: UNKNOWN
